frepr.cp35-win_amd64.pyd
frepr-0.1.1.dist-info/DESCRIPTION.rst
frepr-0.1.1.dist-info/METADATA
frepr-0.1.1.dist-info/RECORD
frepr-0.1.1.dist-info/WHEEL
frepr-0.1.1.dist-info/metadata.json
frepr-0.1.1.dist-info/top_level.txt
