Metadata-Version: 2.0
Name: frepr
Version: 0.1.1
Summary: Fast float repr
Home-page: https://github.com/wemoloh/frepr
Author: Bart Robinson
Author-email: bart@bartrobinson.com
License: BSD 3-Clause License
Platform: UNKNOWN
Classifier: Development Status :: 4 - Beta
Classifier: Intended Audience :: Developers
Classifier: License :: OSI Approved :: BSD License
Classifier: Programming Language :: Python :: 2
Classifier: Programming Language :: Python :: 3
